djqs/__about__.py
djqs/__init__.py
djqs/config.py
djqs/constants.py
djqs/engine.py
djqs/enum.py
djqs/exceptions.py
djqs/fixes.py
djqs/typing.py
djqs/utils.py
djqs/api/__init__.py
djqs/api/helpers.py
djqs/api/main.py
djqs/api/queries.py
djqs/api/tables.py
djqs/db/postgres.py
djqs/models/__init__.py
djqs/models/query.py
djqs/models/table.py
datajunction_query-0.0.41.dist-info/METADATA
datajunction_query-0.0.41.dist-info/WHEEL
datajunction_query-0.0.41.dist-info/licenses/AUTHORS.rst
datajunction_query-0.0.41.dist-info/licenses/LICENSE.txt
datajunction_query-0.0.41.dist-info/RECORD
