Metadata-Version: 2.4
Name: datajunction-query
Version: 0.0.41
Summary: OSS Implementation of a DataJunction Query Service
Project-URL: repository, https://github.com/DataJunction/dj
Author-email: DataJunction Authors <roberto@dealmeida.net>
License: MIT
License-File: AUTHORS.rst
License-File: LICENSE.txt
Classifier: License :: OSI Approved :: MIT License
Classifier: Operating System :: OS Independent
Classifier: Programming Language :: Python :: 3.8
Classifier: Programming Language :: Python :: 3.9
Classifier: Programming Language :: Python :: 3.10
Classifier: Programming Language :: Python :: 3.11
Classifier: Programming Language :: Python :: 3.12
Requires-Python: <4.0,>=3.10
Requires-Dist: accept-types==0.4.1
Requires-Dist: cachelib>=0.4.0
Requires-Dist: duckdb-engine
Requires-Dist: duckdb==0.8.1
Requires-Dist: fastapi>=0.79.0
Requires-Dist: importlib-metadata
Requires-Dist: msgpack>=1.0.3
Requires-Dist: psycopg[async,pool]>=3.2.1
Requires-Dist: pytest-asyncio>=0.24.0
Requires-Dist: pytest-integration>=0.2.3
Requires-Dist: python-dotenv==0.19.2
Requires-Dist: pyyaml>=6.0.1
Requires-Dist: requests<=2.29.0,>=2.28.2
Requires-Dist: rich>=10.16.2
Requires-Dist: snowflake-connector-python>=3.3.1
Requires-Dist: sqlalchemy>=2.0.34
Requires-Dist: tenacity>=9.0.0
Requires-Dist: toml>=0.10.2
Requires-Dist: trino>=0.324.0
Provides-Extra: uvicorn
Requires-Dist: uvicorn[standard]>=0.21.1; extra == 'uvicorn'
